instax/__init__.py
instax/comms.py
instax/debugServer.py
instax/exceptions.py
instax/instaxImage.py
instax/packet.py
instax/print.py
instax/sp2.py
instax/sp3.py
instax/tests/__init__.py
instax/tests/replay.json
instax/tests/testEncodedImage.instax
instax/tests/test_basic.py
instax/tests/test_image.png
instax/tests/test_image_encoder.py
instax/tests/test_premade.py
instax/tests/test_replay.py
instax/tests/test_socket.py
instax/tests/test_sp2.py
instax/tests/test_sp3.py
instax_api-0.8.0.dist-info/METADATA
instax_api-0.8.0.dist-info/LICENSE
instax_api-0.8.0.dist-info/WHEEL
instax_api-0.8.0.dist-info/RECORD
