Metadata-Version: 2.1
Name: instax-api
Version: 0.8.0
Summary: A Python module and app to print photos on the Fujifim Instax Printers
License: MIT
Author: James Sutton
Requires-Python: >=3.10,<4.0
Classifier: License :: OSI Approved :: MIT License
Classifier: Programming Language :: Python :: 3
Classifier: Programming Language :: Python :: 3.10
Classifier: Programming Language :: Python :: 3.11
Requires-Dist: Pillow (>=9.3.0,<10.0.0)
Requires-Dist: loguru (>=0.6.0,<0.7.0)
